odoo/addons/fleet_vehicle_capacity/README.rst
odoo/addons/fleet_vehicle_capacity/__init__.py
odoo/addons/fleet_vehicle_capacity/__manifest__.py
odoo/addons/fleet_vehicle_capacity/i18n/fleet_vehicle_capacity.pot
odoo/addons/fleet_vehicle_capacity/i18n/it.po
odoo/addons/fleet_vehicle_capacity/i18n/pt_BR.po
odoo/addons/fleet_vehicle_capacity/models/__init__.py
odoo/addons/fleet_vehicle_capacity/models/fleet_vehicle.py
odoo/addons/fleet_vehicle_capacity/models/fleet_vehicle_model.py
odoo/addons/fleet_vehicle_capacity/models/res_config_settings.py
odoo/addons/fleet_vehicle_capacity/readme/CONTRIBUTORS.md
odoo/addons/fleet_vehicle_capacity/readme/DESCRIPTION.md
odoo/addons/fleet_vehicle_capacity/readme/USAGE.md
odoo/addons/fleet_vehicle_capacity/static/description/icon.png
odoo/addons/fleet_vehicle_capacity/static/description/index.html
odoo/addons/fleet_vehicle_capacity/tests/__init__.py
odoo/addons/fleet_vehicle_capacity/tests/test_fleet_vehicle_capacity.py
odoo/addons/fleet_vehicle_capacity/views/fleet_vehicle.xml
odoo/addons/fleet_vehicle_capacity/views/fleet_vehicle_model.xml
odoo/addons/fleet_vehicle_capacity/views/res_config_settings.xml
odoo14_addon_fleet_vehicle_capacity-14.0.1.0.1.dev6.dist-info/METADATA
odoo14_addon_fleet_vehicle_capacity-14.0.1.0.1.dev6.dist-info/WHEEL
odoo14_addon_fleet_vehicle_capacity-14.0.1.0.1.dev6.dist-info/top_level.txt
odoo14_addon_fleet_vehicle_capacity-14.0.1.0.1.dev6.dist-info/RECORD
